vnpy_crypto/__init__.py
vnpy_crypto/constant.py
vnpy_crypto-0.1.0.dist-info/LICENSE
vnpy_crypto-0.1.0.dist-info/METADATA
vnpy_crypto-0.1.0.dist-info/WHEEL
vnpy_crypto-0.1.0.dist-info/top_level.txt
vnpy_crypto-0.1.0.dist-info/RECORD
